pythologist/__init__.py
pythologist/image.py
pythologist/read.py
pythologist/selection.py
pythologist/spatial.py
pythologist/test.py
pythologist/write.py
pythologist-1.0.2.dist-info/LICENSE
pythologist-1.0.2.dist-info/METADATA
pythologist-1.0.2.dist-info/WHEEL
pythologist-1.0.2.dist-info/top_level.txt
pythologist-1.0.2.dist-info/RECORD
