Metadata-Version: 2.1
Name: pythologist
Version: 1.0.2
Summary: inForm PerkinElmer Reader - Python interface to read outputs of the PerkinElmer inForm software
Home-page: https://github.com/jason-weirather/pythologist
Author: Jason L Weirather
Author-email: jason.weirather@gmail.com
License: Apache License, Version 2.0
Keywords: bioinformatics
Platform: UNKNOWN
Classifier: Development Status :: 3 - Alpha
Classifier: Intended Audience :: Science/Research
Classifier: Topic :: Scientific/Engineering :: Bio-Informatics
Classifier: License :: OSI Approved :: Apache Software License
Requires-Dist: pandas (>=0.23.0)
Requires-Dist: numpy
Requires-Dist: scipy
Requires-Dist: h5py
Requires-Dist: imageio
Requires-Dist: tables
Requires-Dist: pythologist-image-utilities (>=1.0.2)
Provides-Extra: test
Requires-Dist: pythologist-test-images ; extra == 'test'
